odoo10_addon_mrp_repair_discount-10.0.1.0.0-py2.7-nspkg.pth
odoo/addons/mrp_repair_discount/README.rst
odoo/addons/mrp_repair_discount/__init__.py
odoo/addons/mrp_repair_discount/__manifest__.py
odoo/addons/mrp_repair_discount/models/__init__.py
odoo/addons/mrp_repair_discount/models/mrp_repair.py
odoo/addons/mrp_repair_discount/tests/__init__.py
odoo/addons/mrp_repair_discount/tests/test_mrp_repair_discount.py
odoo/addons/mrp_repair_discount/views/mrp_repair_view.xml
odoo10_addon_mrp_repair_discount-10.0.1.0.0.dist-info/DESCRIPTION.rst
odoo10_addon_mrp_repair_discount-10.0.1.0.0.dist-info/METADATA
odoo10_addon_mrp_repair_discount-10.0.1.0.0.dist-info/RECORD
odoo10_addon_mrp_repair_discount-10.0.1.0.0.dist-info/WHEEL
odoo10_addon_mrp_repair_discount-10.0.1.0.0.dist-info/metadata.json
odoo10_addon_mrp_repair_discount-10.0.1.0.0.dist-info/namespace_packages.txt
odoo10_addon_mrp_repair_discount-10.0.1.0.0.dist-info/top_level.txt
